aliro_aqn/__init__.py
aliro_aqn/api_client.py
aliro_aqn/configuration.py
aliro_aqn/exceptions.py
aliro_aqn/rest.py
aliro_aqn/api/__init__.py
aliro_aqn/api/authentication_api.py
aliro_aqn/api/submissions_api.py
aliro_aqn/api/user_api.py
aliro_aqn/models/__init__.py
aliro_aqn/models/api_key.py
aliro_aqn/models/api_key_response.py
aliro_aqn/models/basic_success.py
aliro_aqn/models/change_password_parameters.py
aliro_aqn/models/classical_channel.py
aliro_aqn/models/credentials_basic.py
aliro_aqn/models/login_response.py
aliro_aqn/models/memory.py
aliro_aqn/models/memory_base.py
aliro_aqn/models/memory_input.py
aliro_aqn/models/memory_output.py
aliro_aqn/models/memory_output_all_of.py
aliro_aqn/models/node.py
aliro_aqn/models/quantum_connection.py
aliro_aqn/models/request.py
aliro_aqn/models/submission_aqn.py
aliro_aqn/models/submission_aqn_base.py
aliro_aqn/models/submission_aqn_input.py
aliro_aqn/models/submission_aqn_output.py
aliro_aqn/models/submission_aqn_output_all_of.py
aliro_aqn/models/update_user_information_parameters.py
aliro_aqn/models/user_info.py
aliro_aqn-1.0.0.dist-info/METADATA
aliro_aqn-1.0.0.dist-info/WHEEL
aliro_aqn-1.0.0.dist-info/top_level.txt
aliro_aqn-1.0.0.dist-info/RECORD
