Metadata-Version: 2.1
Name: aliro-aqn
Version: 1.0.0
Summary: Aliro Q.Network
Home-page: UNKNOWN
Author: OpenAPI Generator community
Author-email: nick@aliroquantum.com
License: UNKNOWN
Keywords: OpenAPI,OpenAPI-Generator,Aliro Q.Network
Platform: UNKNOWN
Requires-Dist: certifi
Requires-Dist: python-dateutil
Requires-Dist: six (>=1.10)
Requires-Dist: sseclient-py (>=1.7)
Requires-Dist: urllib3 (>=1.15)
